crucible_sdk.py
crucible_sdk-1.0.1.dist-info/METADATA
crucible_sdk-1.0.1.dist-info/WHEEL
crucible_sdk-1.0.1.dist-info/entry_points.txt
crucible_sdk-1.0.1.dist-info/RECORD
