Metadata-Version: 2.1
Name: crucible-sdk
Version: 1.0.1
Summary: A simple tool for generating client libraries from OpenAPI schemas
Author: JHart96
Author-email: jordan.da.hart@gmail.com
Requires-Python: >=3.10,<4.0
Classifier: Programming Language :: Python :: 3
Classifier: Programming Language :: Python :: 3.10
Classifier: Programming Language :: Python :: 3.11
Classifier: Programming Language :: Python :: 3.12
Requires-Dist: click (>=8.1.7,<9.0.0)
Requires-Dist: pyyaml (>=6.0.1,<7.0.0)
